{
  "www.fotokonijnenberg.nl": {
    "last_status": 200,
    "last_attempt": "2026-05-09T13:43:16.433Z",
    "consecutive_fails": 0,
    "preferred_method": null
  },
  "www.coolblue.nl": {
    "last_status": 200,
    "last_attempt": "2026-05-09T13:43:32.516Z",
    "consecutive_fails": 0,
    "preferred_method": "json-ld"
  },
  "www.cameranu.nl": {
    "last_status": 403,
    "last_attempt": "2026-05-09T13:43:46.704Z",
    "consecutive_fails": 0,
    "preferred_method": null
  },
  "www.mediamarkt.nl": {
    "last_status": 200,
    "last_attempt": "2026-05-09T13:44:04.850Z",
    "consecutive_fails": 0,
    "preferred_method": "heuristic"
  },
  "www.amazon.nl": {
    "last_status": 200,
    "last_attempt": "2026-05-09T13:44:18.235Z",
    "consecutive_fails": 0,
    "preferred_method": "heuristic"
  },
  "www.bol.com": {
    "last_status": 200,
    "last_attempt": "2026-05-09T13:46:39.535Z",
    "consecutive_fails": 0,
    "preferred_method": null
  },
  "www.bcc.nl": {
    "last_status": 404,
    "last_attempt": "2026-05-09T13:44:41.964Z",
    "consecutive_fails": 0,
    "preferred_method": null
  },
  "www.kamera-express.nl": {
    "last_status": 200,
    "last_attempt": "2026-05-09T13:45:02.450Z",
    "consecutive_fails": 0,
    "preferred_method": null
  },
  "www.fotodevakman.nl": {
    "last_status": 403,
    "last_attempt": "2026-05-09T13:45:13.511Z",
    "consecutive_fails": 0,
    "preferred_method": null
  },
  "www.canon.nl": {
    "last_status": 403,
    "last_attempt": "2026-05-09T13:45:24.112Z",
    "consecutive_fails": 0,
    "preferred_method": null
  },
  "www.neboweb.nl": {
    "last_status": 200,
    "last_attempt": "2026-05-09T13:45:29.270Z",
    "consecutive_fails": 0,
    "preferred_method": "json-ld"
  },
  "melskensvenray.nl": {
    "last_status": 200,
    "last_attempt": "2026-05-09T13:45:37.565Z",
    "consecutive_fails": 0,
    "preferred_method": "json-ld"
  },
  "www.mediamarkt.be": {
    "last_status": 200,
    "last_attempt": "2026-05-09T13:45:44.835Z",
    "consecutive_fails": 0,
    "preferred_method": "heuristic"
  },
  "www.coolblue.be": {
    "last_status": 200,
    "last_attempt": "2026-05-09T13:46:04.320Z",
    "consecutive_fails": 0,
    "preferred_method": "json-ld"
  },
  "www.vandenborre.be": {
    "last_status": 200,
    "last_attempt": "2026-05-09T13:46:18.435Z",
    "consecutive_fails": 0,
    "preferred_method": "heuristic"
  },
  "www.krefel.be": {
    "last_status": 500,
    "last_attempt": "2026-05-09T13:46:29.676Z",
    "consecutive_fails": 0,
    "preferred_method": null
  },
  "www.amazon.com.be": {
    "last_status": 200,
    "last_attempt": "2026-05-09T13:46:44.997Z",
    "consecutive_fails": 0,
    "preferred_method": "heuristic"
  },
  "www.nl.fnac.be": {
    "last_status": 403,
    "last_attempt": "2026-05-09T13:46:59.610Z",
    "consecutive_fails": 0,
    "preferred_method": null
  },
  "www.saturn.de": {
    "last_status": 403,
    "last_attempt": "2026-05-09T13:47:17.294Z",
    "consecutive_fails": 0,
    "preferred_method": null
  },
  "www.mediamarkt.de": {
    "last_status": 200,
    "last_attempt": "2026-05-09T13:47:35.780Z",
    "consecutive_fails": 0,
    "preferred_method": "heuristic"
  },
  "www.amazon.de": {
    "last_status": 200,
    "last_attempt": "2026-05-09T13:47:48.649Z",
    "consecutive_fails": 0,
    "preferred_method": "heuristic"
  },
  "www.foto-erhardt.de": {
    "last_status": 200,
    "last_attempt": "2026-05-09T13:47:56.904Z",
    "consecutive_fails": 0,
    "preferred_method": "heuristic"
  },
  "www.fotokoch.de": {
    "last_status": 200,
    "last_attempt": "2026-05-09T13:48:09.865Z",
    "consecutive_fails": 0,
    "preferred_method": null
  },
  "www.calumetphoto.de": {
    "last_status": 200,
    "last_attempt": "2026-05-08T13:48:37.503Z",
    "consecutive_fails": 0,
    "preferred_method": "json-ld"
  },
  "www.foto-mundus.de": {
    "last_status": 404,
    "last_attempt": "2026-05-09T13:48:33.084Z",
    "consecutive_fails": 0,
    "preferred_method": null
  },
  "www.fotomeyer.de": {
    "last_status": 200,
    "last_attempt": "2026-05-09T13:48:39.291Z",
    "consecutive_fails": 0,
    "preferred_method": "meta-tag"
  },
  "www.fotobrenner.de": {
    "last_status": 404,
    "last_attempt": "2026-05-09T13:48:53.936Z",
    "consecutive_fails": 0,
    "preferred_method": null
  },
  "www.canon.de": {
    "last_status": 403,
    "last_attempt": "2026-05-09T13:49:03.971Z",
    "consecutive_fails": 0,
    "preferred_method": null
  },
  "www.amazon.fr": {
    "last_status": 200,
    "last_attempt": "2026-05-09T13:49:16.237Z",
    "consecutive_fails": 0,
    "preferred_method": "heuristic"
  },
  "www.fnac.com": {
    "last_status": 403,
    "last_attempt": "2026-05-09T13:49:24.493Z",
    "consecutive_fails": 0,
    "preferred_method": null
  },
  "www.darty.com": {
    "last_status": 403,
    "last_attempt": "2026-05-09T13:49:30.248Z",
    "consecutive_fails": 0,
    "preferred_method": null
  },
  "www.boulanger.com": {
    "last_status": 400,
    "last_attempt": "2026-05-09T13:49:34.894Z",
    "consecutive_fails": 0,
    "preferred_method": null
  },
  "www.digit-photo.com": {
    "last_status": 200,
    "last_attempt": "2026-05-09T13:50:04.437Z",
    "consecutive_fails": 0,
    "preferred_method": null
  },
  "www.missnumerique.com": {
    "last_status": 200,
    "last_attempt": "2026-05-09T13:50:09.473Z",
    "consecutive_fails": 0,
    "preferred_method": "json-ld"
  },
  "store.canon.fr": {
    "last_status": 403,
    "last_attempt": "2026-05-09T13:49:41.653Z",
    "consecutive_fails": 0,
    "preferred_method": null
  },
  "www.canon.fr": {
    "last_status": 403,
    "last_attempt": "2026-05-09T13:49:48.088Z",
    "consecutive_fails": 0,
    "preferred_method": null
  },
  "www.pixmania.com": {
    "last_status": 200,
    "last_attempt": "2026-05-09T13:49:53.275Z",
    "consecutive_fails": 0,
    "preferred_method": "json-ld"
  },
  "geizhals.de": {
    "last_status": 403,
    "last_attempt": "2026-05-09T13:50:27.751Z",
    "consecutive_fails": 0,
    "preferred_method": null
  },
  "www.idealo.de": {
    "last_status": 503,
    "last_attempt": "2026-05-09T13:50:32.393Z",
    "consecutive_fails": 0,
    "preferred_method": null
  },
  "www.idealo.fr": {
    "last_status": 503,
    "last_attempt": "2026-05-09T13:50:37.503Z",
    "consecutive_fails": 0,
    "preferred_method": null
  },
  "www.calumet.de": {
    "last_status": 200,
    "last_attempt": "2026-05-09T13:48:22.178Z",
    "consecutive_fails": 0,
    "preferred_method": "json-ld"
  },
  "www.cameraland.nl": {
    "last_status": 200,
    "last_attempt": "2026-05-09T13:50:54.636Z",
    "consecutive_fails": 0,
    "preferred_method": "json-ld"
  },
  "www.grobet.be": {
    "last_status": 200,
    "last_attempt": "2026-05-09T13:51:10.642Z",
    "consecutive_fails": 0,
    "preferred_method": "json-ld"
  },
  "digimaxx.nl": {
    "last_status": 200,
    "last_attempt": "2026-05-09T13:51:18.857Z",
    "consecutive_fails": 0,
    "preferred_method": "heuristic"
  },
  "www.cameradeals.nl": {
    "last_status": 200,
    "last_attempt": "2026-05-09T13:51:24.636Z",
    "consecutive_fails": 0,
    "preferred_method": "heuristic"
  },
  "www.kaufland.de": {
    "last_status": 403,
    "last_attempt": "2026-05-09T13:51:30.661Z",
    "consecutive_fails": 0,
    "preferred_method": null
  }
}